{
  "name": "joy",
  "word": "symbol",
  "rules": {
    "source_file": {
      "type": "REPEAT",
      "content": {
        "type": "SYMBOL",
        "name": "_item"
      }
    },
    "_item": {
      "type": "CHOICE",
      "members": [
        {
          "type": "SYMBOL",
          "name": "definition"
        },
        {
          "type": "SYMBOL",
          "name": "statement"
        },
        {
          "type": "SYMBOL",
          "name": "library_keyword"
        },
        {
          "type": "SYMBOL",
          "name": "shell_escape"
        },
        {
          "type": "SYMBOL",
          "name": "semicolon"
        },
        {
          "type": "STRING",
          "value": "."
        }
      ]
    },
    "shell_escape": {
      "type": "TOKEN",
      "content": {
        "type": "SEQ",
        "members": [
          {
            "type": "STRING",
            "value": "$"
          },
          {
            "type": "PATTERN",
            "value": "[^\\n]*"
          }
        ]
      }
    },
    "library_keyword": {
      "type": "CHOICE",
      "members": [
        {
          "type": "STRING",
          "value": "LIBRA"
        },
        {
          "type": "STRING",
          "value": "DEFINE"
        },
        {
          "type": "STRING",
          "value": "HIDE"
        },
        {
          "type": "STRING",
          "value": "IN"
        },
        {
          "type": "STRING",
          "value": "END"
        },
        {
          "type": "STRING",
          "value": "MODULE"
        },
        {
          "type": "STRING",
          "value": "PRIVATE"
        },
        {
          "type": "STRING",
          "value": "PUBLIC"
        },
        {
          "type": "STRING",
          "value": "CONST"
        },
        {
          "type": "STRING",
          "value": "INLINE"
        }
      ]
    },
    "definition": {
      "type": "SEQ",
      "members": [
        {
          "type": "FIELD",
          "name": "name",
          "content": {
            "type": "SYMBOL",
            "name": "symbol"
          }
        },
        {
          "type": "STRING",
          "value": "=="
        },
        {
          "type": "CHOICE",
          "members": [
            {
              "type": "FIELD",
              "name": "body",
              "content": {
                "type": "SYMBOL",
                "name": "_body"
              }
            },
            {
              "type": "BLANK"
            }
          ]
        },
        {
          "type": "CHOICE",
          "members": [
            {
              "type": "STRING",
              "value": "."
            },
            {
              "type": "STRING",
              "value": ";"
            }
          ]
        }
      ]
    },
    "_body": {
      "type": "REPEAT1",
      "content": {
        "type": "SYMBOL",
        "name": "_expression"
      }
    },
    "statement": {
      "type": "SEQ",
      "members": [
        {
          "type": "REPEAT1",
          "content": {
            "type": "SYMBOL",
            "name": "_expression"
          }
        },
        {
          "type": "STRING",
          "value": "."
        }
      ]
    },
    "_expression": {
      "type": "CHOICE",
      "members": [
        {
          "type": "SYMBOL",
          "name": "_literal"
        },
        {
          "type": "SYMBOL",
          "name": "quotation"
        },
        {
          "type": "SYMBOL",
          "name": "set_literal"
        },
        {
          "type": "SYMBOL",
          "name": "native_vector"
        },
        {
          "type": "SYMBOL",
          "name": "native_matrix"
        },
        {
          "type": "SYMBOL",
          "name": "symbol"
        },
        {
          "type": "SYMBOL",
          "name": "operator"
        }
      ]
    },
    "_literal": {
      "type": "CHOICE",
      "members": [
        {
          "type": "SYMBOL",
          "name": "integer"
        },
        {
          "type": "SYMBOL",
          "name": "float"
        },
        {
          "type": "SYMBOL",
          "name": "character"
        },
        {
          "type": "SYMBOL",
          "name": "string"
        },
        {
          "type": "SYMBOL",
          "name": "interpolated_string"
        },
        {
          "type": "SYMBOL",
          "name": "boolean"
        },
        {
          "type": "SYMBOL",
          "name": "null"
        }
      ]
    },
    "integer": {
      "type": "TOKEN",
      "content": {
        "type": "SEQ",
        "members": [
          {
            "type": "CHOICE",
            "members": [
              {
                "type": "STRING",
                "value": "-"
              },
              {
                "type": "BLANK"
              }
            ]
          },
          {
            "type": "PATTERN",
            "value": "[0-9]+"
          }
        ]
      }
    },
    "float": {
      "type": "TOKEN",
      "content": {
        "type": "SEQ",
        "members": [
          {
            "type": "CHOICE",
            "members": [
              {
                "type": "STRING",
                "value": "-"
              },
              {
                "type": "BLANK"
              }
            ]
          },
          {
            "type": "PATTERN",
            "value": "[0-9]+"
          },
          {
            "type": "STRING",
            "value": "."
          },
          {
            "type": "PATTERN",
            "value": "[0-9]+"
          }
        ]
      }
    },
    "character": {
      "type": "TOKEN",
      "content": {
        "type": "SEQ",
        "members": [
          {
            "type": "STRING",
            "value": "'"
          },
          {
            "type": "CHOICE",
            "members": [
              {
                "type": "PATTERN",
                "value": "[^\\\\']"
              },
              {
                "type": "PATTERN",
                "value": "\\\\[btnvfr\"'\\\\]"
              },
              {
                "type": "PATTERN",
                "value": "\\\\[0-7]{1,3}"
              }
            ]
          }
        ]
      }
    },
    "string": {
      "type": "TOKEN",
      "content": {
        "type": "SEQ",
        "members": [
          {
            "type": "STRING",
            "value": "\""
          },
          {
            "type": "REPEAT",
            "content": {
              "type": "CHOICE",
              "members": [
                {
                  "type": "PATTERN",
                  "value": "[^\"\\\\]"
                },
                {
                  "type": "PATTERN",
                  "value": "\\\\[btnvfr\"'\\\\]"
                },
                {
                  "type": "PATTERN",
                  "value": "\\\\[0-7]{1,3}"
                }
              ]
            }
          },
          {
            "type": "STRING",
            "value": "\""
          }
        ]
      }
    },
    "boolean": {
      "type": "CHOICE",
      "members": [
        {
          "type": "STRING",
          "value": "true"
        },
        {
          "type": "STRING",
          "value": "false"
        }
      ]
    },
    "null": {
      "type": "STRING",
      "value": "null"
    },
    "quotation": {
      "type": "SEQ",
      "members": [
        {
          "type": "STRING",
          "value": "["
        },
        {
          "type": "REPEAT",
          "content": {
            "type": "SYMBOL",
            "name": "_quotation_item"
          }
        },
        {
          "type": "STRING",
          "value": "]"
        }
      ]
    },
    "_quotation_item": {
      "type": "CHOICE",
      "members": [
        {
          "type": "SYMBOL",
          "name": "_expression"
        },
        {
          "type": "SYMBOL",
          "name": "cons_operator"
        }
      ]
    },
    "cons_operator": {
      "type": "STRING",
      "value": ":"
    },
    "set_literal": {
      "type": "SEQ",
      "members": [
        {
          "type": "STRING",
          "value": "{"
        },
        {
          "type": "REPEAT",
          "content": {
            "type": "SYMBOL",
            "name": "_expression"
          }
        },
        {
          "type": "STRING",
          "value": "}"
        }
      ]
    },
    "native_vector": {
      "type": "SEQ",
      "members": [
        {
          "type": "STRING",
          "value": "v["
        },
        {
          "type": "REPEAT",
          "content": {
            "type": "SYMBOL",
            "name": "_number"
          }
        },
        {
          "type": "STRING",
          "value": "]"
        }
      ]
    },
    "native_matrix": {
      "type": "SEQ",
      "members": [
        {
          "type": "STRING",
          "value": "m["
        },
        {
          "type": "REPEAT",
          "content": {
            "type": "SYMBOL",
            "name": "matrix_row"
          }
        },
        {
          "type": "STRING",
          "value": "]"
        }
      ]
    },
    "matrix_row": {
      "type": "SEQ",
      "members": [
        {
          "type": "STRING",
          "value": "["
        },
        {
          "type": "REPEAT",
          "content": {
            "type": "SYMBOL",
            "name": "_number"
          }
        },
        {
          "type": "STRING",
          "value": "]"
        }
      ]
    },
    "_number": {
      "type": "CHOICE",
      "members": [
        {
          "type": "SYMBOL",
          "name": "integer"
        },
        {
          "type": "SYMBOL",
          "name": "float"
        }
      ]
    },
    "symbol": {
      "type": "PATTERN",
      "value": "[a-zA-Z_][a-zA-Z0-9_\\-?!]*"
    },
    "operator": {
      "type": "CHOICE",
      "members": [
        {
          "type": "STRING",
          "value": "+"
        },
        {
          "type": "STRING",
          "value": "-"
        },
        {
          "type": "STRING",
          "value": "*"
        },
        {
          "type": "STRING",
          "value": "/"
        },
        {
          "type": "STRING",
          "value": "="
        },
        {
          "type": "STRING",
          "value": "<"
        },
        {
          "type": "STRING",
          "value": ">"
        },
        {
          "type": "STRING",
          "value": "<="
        },
        {
          "type": "STRING",
          "value": ">="
        },
        {
          "type": "STRING",
          "value": "!="
        },
        {
          "type": "STRING",
          "value": ">set"
        },
        {
          "type": "STRING",
          "value": ">dict"
        },
        {
          "type": "STRING",
          "value": ">vec"
        },
        {
          "type": "STRING",
          "value": ">mat"
        },
        {
          "type": "STRING",
          "value": ">list"
        },
        {
          "type": "STRING",
          "value": ">json"
        },
        {
          "type": "STRING",
          "value": "json>"
        },
        {
          "type": "STRING",
          "value": "v+"
        },
        {
          "type": "STRING",
          "value": "v-"
        },
        {
          "type": "STRING",
          "value": "v*"
        },
        {
          "type": "STRING",
          "value": "v/"
        },
        {
          "type": "STRING",
          "value": "m+"
        },
        {
          "type": "STRING",
          "value": "m-"
        },
        {
          "type": "STRING",
          "value": "m*"
        },
        {
          "type": "STRING",
          "value": "m/"
        }
      ]
    },
    "semicolon": {
      "type": "STRING",
      "value": ";"
    },
    "line_comment": {
      "type": "TOKEN",
      "content": {
        "type": "SEQ",
        "members": [
          {
            "type": "STRING",
            "value": "#"
          },
          {
            "type": "PATTERN",
            "value": ".*"
          }
        ]
      }
    }
  },
  "extras": [
    {
      "type": "PATTERN",
      "value": "\\s"
    },
    {
      "type": "SYMBOL",
      "name": "line_comment"
    },
    {
      "type": "SYMBOL",
      "name": "block_comment"
    }
  ],
  "conflicts": [],
  "precedences": [],
  "externals": [
    {
      "type": "SYMBOL",
      "name": "block_comment"
    },
    {
      "type": "SYMBOL",
      "name": "interpolated_string"
    }
  ],
  "inline": [],
  "supertypes": []
}
